AgilisysDailyTender/Bluelight.py
AgilisysDailyTender/Classification.py
AgilisysDailyTender/ContractsFinder.py
AgilisysDailyTender/Keywords.py
AgilisysDailyTender/Proactis.py
AgilisysDailyTender/__init__.py
AgilisysDailyTender/main.py
AgilisysDailyTender/models/en_core_web_sm/__init__.py
AgilisysDailyTender/models/en_core_web_sm/meta.json
AgilisysDailyTender/models/en_core_web_sm/__pycache__/__init__.cpython-311.pyc
AgilisysDailyTender/models/en_core_web_sm/en_core_web_sm-3.5.0/LICENSE
AgilisysDailyTender/models/en_core_web_sm/en_core_web_sm-3.5.0/LICENSES_SOURCES
AgilisysDailyTender/models/en_core_web_sm/en_core_web_sm-3.5.0/README.md
AgilisysDailyTender/models/en_core_web_sm/en_core_web_sm-3.5.0/accuracy.json
AgilisysDailyTender/models/en_core_web_sm/en_core_web_sm-3.5.0/config.cfg
AgilisysDailyTender/models/en_core_web_sm/en_core_web_sm-3.5.0/meta.json
AgilisysDailyTender/models/en_core_web_sm/en_core_web_sm-3.5.0/tokenizer
AgilisysDailyTender/models/en_core_web_sm/en_core_web_sm-3.5.0/attribute_ruler/patterns
AgilisysDailyTender/models/en_core_web_sm/en_core_web_sm-3.5.0/lemmatizer/lookups/lookups.bin
AgilisysDailyTender/models/en_core_web_sm/en_core_web_sm-3.5.0/ner/cfg
AgilisysDailyTender/models/en_core_web_sm/en_core_web_sm-3.5.0/ner/model
AgilisysDailyTender/models/en_core_web_sm/en_core_web_sm-3.5.0/ner/moves
AgilisysDailyTender/models/en_core_web_sm/en_core_web_sm-3.5.0/parser/cfg
AgilisysDailyTender/models/en_core_web_sm/en_core_web_sm-3.5.0/parser/model
AgilisysDailyTender/models/en_core_web_sm/en_core_web_sm-3.5.0/parser/moves
AgilisysDailyTender/models/en_core_web_sm/en_core_web_sm-3.5.0/senter/cfg
AgilisysDailyTender/models/en_core_web_sm/en_core_web_sm-3.5.0/senter/model
AgilisysDailyTender/models/en_core_web_sm/en_core_web_sm-3.5.0/tagger/cfg
AgilisysDailyTender/models/en_core_web_sm/en_core_web_sm-3.5.0/tagger/model
AgilisysDailyTender/models/en_core_web_sm/en_core_web_sm-3.5.0/tok2vec/cfg
AgilisysDailyTender-1.0.1.dist-info/METADATA
AgilisysDailyTender-1.0.1.dist-info/WHEEL
AgilisysDailyTender-1.0.1.dist-info/top_level.txt
AgilisysDailyTender-1.0.1.dist-info/RECORD
